LICENSE
MANIFEST.in
README.rst
setup.py
polls/__init__.py
polls/admin.py
polls/models.py
polls/tests.py
polls/urls.py
polls/views.py
polls/static/polls/style.css
polls/static/polls/images/background.png
polls/templates/polls/detail.html
polls/templates/polls/index.html
polls/templates/polls/results.html
tolerious_polls.egg-info/PKG-INFO
tolerious_polls.egg-info/SOURCES.txt
tolerious_polls.egg-info/dependency_links.txt
tolerious_polls.egg-info/top_level.txt